multiLineLambda/__init__.py
multiLineLambda/lambdaFunction.py
multiLineLambda-0.0.3.dist-info/LICENSE.md
multiLineLambda-0.0.3.dist-info/METADATA
multiLineLambda-0.0.3.dist-info/WHEEL
multiLineLambda-0.0.3.dist-info/top_level.txt
multiLineLambda-0.0.3.dist-info/RECORD
