Metadata-Version: 2.1
Name: multiLineLambda
Version: 0.0.3
Summary: A package for writing multiple lines in a lambda function.
Home-page: https://github.com/NotShrirang/Multiline-lambda-Function
Author: Shrirang Mahajan
Author-email: shrirangmahajan123@gmail.com
Project-URL: Bug Tracker, https://github.com/NotShrirang/Multiline-lambda-Function/issues
Classifier: Programming Language :: Python :: 3
Classifier: License :: OSI Approved :: MIT License
Classifier: Operating System :: OS Independent
Requires-Python: >=3.6
License-File: LICENSE.md
